fbdata/__init__.py
fbdata/fbdata.py
football_data-0.1.20.dist-info/DESCRIPTION.rst
football_data-0.1.20.dist-info/METADATA
football_data-0.1.20.dist-info/RECORD
football_data-0.1.20.dist-info/WHEEL
football_data-0.1.20.dist-info/metadata.json
football_data-0.1.20.dist-info/top_level.txt
