Metadata-Version: 2.0
Name: football-data
Version: 0.1.20
Summary: Wrapper over the data sets provided at http://www.football-data.co.uk/data.php to easily get historical football data like shots on goal, scored goals etc. from all major european football/soccer teams.
Home-page: https://github.com/olalidmark/football-data
Author: fantomen
Author-email: olalidmark@gmail.com
License: MIT
Keywords: football,soccer,metrics,sports,statistics
Platform: UNKNOWN
Classifier: Development Status :: 4 - Beta
Classifier: Intended Audience :: Developers
Classifier: License :: OSI Approved :: MIT License
Classifier: Programming Language :: Python :: 2
Classifier: Programming Language :: Python :: 2.7
Requires-Dist: numpy
